pyw/__init__.py
pyw/music21/__init__.py
pyw_music21-0.0.0.post2.dist-info/METADATA
pyw_music21-0.0.0.post2.dist-info/WHEEL
pyw_music21-0.0.0.post2.dist-info/licenses/LICENSE
pyw_music21-0.0.0.post2.dist-info/RECORD
