Metadata-Version: 2.4
Name: pyw-music21
Version: 0.0.0.post2
Summary: Music21 stub generator (placeholder)
Project-URL: Homepage, https://github.com/pythonWoods/pyw-music21
Project-URL: Documentation, https://pythonwoods.dev/docs/pyw-music21/latest/
Project-URL: Issues, https://github.com/pythonWoods/pyw-music21/issues
Project-URL: Changelog, https://github.com/pythonWoods/pyw-music21/releases
Author: pythonWoods
License: MIT
License-File: LICENSE
Classifier: Development Status :: 2 - Pre-Alpha
Classifier: License :: OSI Approved :: MIT License
Classifier: Programming Language :: Python :: 3 :: Only
Classifier: Programming Language :: Python :: 3.11
Classifier: Typing :: Typed
Requires-Python: >=3.9
Requires-Dist: music21>=9
Requires-Dist: pyw-core>=0.0.0
